Extra_Lab/MUX/mux.v
// 2-1 MUX Gate Level
module mux_2to1_gate (
    input a,
    input b,
    input s,
    output y
);

    wire not_s;
    wire a_sel, b_sel;

    not (not_s, s);
    and (a_sel, a, not_s);
    and (b_sel, b, s);
    or (y, a_sel, b_sel);

endmodule

// 2-1 MUX Data Flow
module mux_2to1 (
    input a, 
    input b,
    input s,
    output y
);

    assign y = s ? b : a;

endmodule

// 4-1 MUX Structural
module mux_4to1_structural (
    input a,
    input b,
    input c,
    input d,
    input [1:0] s,
    output y
);

    wire mux_ab;
    wire mux_cd;

    mux_2to1 m1 (
        .a(a),
        .b(b),
        .s(s[0]),
        .y(mux_ab)
    );

    mux_2to1 m2 (
        .a(c),
        .b(d),
        .s(s[0]),
        .y(mux_cd)
    );

    mux_2to1 m3 (
        .a(mux_ab),
        .b(mux_cd),
        .s(s[1]),
        .y(y)
    );

endmodule

// 4-1 MUX Behavioral 
module mux_4to1 (
    input a,
    input b,
    input c,
    input d,
    input [1:0] s,
    output reg y
);

    always @(*) begin
        case (s)
            2'b00: y = a;
            2'b01: y = b;
            2'b10: y = c;
            2'b11: y = d;
            default: y = 1'bx;
        endcase
    end

endmodule

// 8-1 MUX Structural
module mux_8to1_structural (
    input [7:0] d,
    input [2:0] s,
    output y
);

    wire mux_lower;
    wire mux_upper;

    mux_4to1 mux_low (
        .a(d[0]),
        .b(d[1]),
        .c(d[2]),
        .d(d[3]),
        .s(s[1:0]),
        .y(mux_lower)
    );

    mux_4to1 mux_high (
        .a(d[4]),
        .b(d[5]),
        .c(d[6]),
        .d(d[7]),
        .s(s[1:0]),
        .y(mux_upper)
    );

    mux_2to1 mux_final (
        .a(mux_lower),
        .b(mux_upper),
        .s(s[2]),
        .y(y)
    );

endmodule

// Parameterized MUX N-bit 2-to-1 MUX
module param_mux_2to1 #(
    parameter WIDTH = 8
)(
    input [WIDTH-1:0] a,
    input [WIDTH-1:0] b,
    input s,
    output [WIDTH-1:0] y
);

    assign y = s ? b : a;

endmodule

Extra_Lab/MUX/tb_mux.v
`timescale 1ns/1ps

module tb_mux;

    // Signals for MUX 2-1 Gate Level & Data Flow
    reg a2, b2, s2;
    wire y2_gate;
    wire y2_dataflow;

    // Signals for MUX 4-1 Structural & Behavioral
    reg a4, b4, c4, d4;
    reg [1:0] s4;
    wire y4_structural;
    wire y4_behavioral;

    // Signals for MUX 8-1 Structural
    reg [7:0] d8;
    reg [2:0] s8;
    wire y8_structural;

    // For loop variable
    integer i;

    mux_2to1_gate uut_mux2_gate (
        .a(a2),
        .b(b2),
        .s(s2),
        .y(y2_gate)
    );

    // Signals for Parameterized MUX 2-1
    parameter TEST_WIDTH = 4;
    reg [TEST_WIDTH-1:0] param_a;
    reg [TEST_WIDTH-1:0] param_b;
    reg param_s;
    wire [TEST_WIDTH-1:0] param_y;

    // Instances
    mux_2to1 uut_mux2_dataflow (
        .a(a2),
        .b(b2),
        .s(s2),
        .y(y2_dataflow)
    );

    mux_4to1_structural uut_mux4_structural (
        .a(a4),
        .b(b4),
        .c(c4),
        .d(d4),
        .s(s4),
        .y(y4_structural)
    );

    mux_4to1 uut_mux4_behavioral (
        .a(a4),
        .b(b4),
        .c(c4),
        .d(d4),
        .s(s4),
        .y(y4_behavioral)
    );

    mux_8to1_structural uut_mux8_structural (
        .d(d8),
        .s(s8),
        .y(y8_structural)
    );

    param_mux_2to1 #(
        .WIDTH(TEST_WIDTH)
    ) uut_param_mux2 (
        .a(param_a),
        .b(param_b),
        .s(param_s),
        .y(param_y)
    );

    // TESTBENCH START
    initial begin
        // Testbench for MUX 2:1 Gate Level & Data Flow
        $display("====================================");
        $display("   TESTBENCH MUX 2:1                ");
        $display("====================================");
        $display("Time\t   A  B  S | Y_Gate    Y_DF");
        $display("------------------------------------");

        // Case 1: s2 = 0, a = 0, b = 1 => y = 0
        a2 = 1'b0; b2 = 1'b1; s2 = 1'b0;
        #10;
        $display("%0dns\t %b %b %b | %b    %b", $time, a2, b2, s2, y2_gate, y2_dataflow);

        // Case 2: s2 = 1, a = 0, b = 1 => y = 1
        a2 = 1'b0; b2 = 1'b1; s2 = 1'b1;
        #10; 
        $display("%0dns\t %b %b %b | %b    %b", $time, a2, b2, s2, y2_gate, y2_dataflow);

        // Case 3: s2 = 0, a = 1, b = 0 => y = 1
        a2 = 1'b1; b2 = 1'b0; s2 = 1'b0;
        #10; 
        $display("%0dns\t %b %b %b | %b    %b", $time, a2, b2, s2, y2_gate, y2_dataflow);

        // Case 4: s2 = 1, a = 1, b = 0 => y = 0
        a2 = 1'b1; b2 = 1'b0; s2 = 1'b1;
        #10; 
        $display("%0dns\t %b %b %b | %b    %b", $time, a2, b2, s2, y2_gate, y2_dataflow);

        // Testbench for MUX 4:1 Structural & Behavioral
        $display("====================================");
        $display("   TESTBENCH MUX 4:1                ");
        $display("====================================");
        $display("Time\t   A  B  C  D | S | Y_Struct    Y_Behave");
        $display("------------------------------------╝");

        // Case 1: s4 = 00, a = 0, b = 1, c = 0, d = 1 => y = 0
        a4 = 1'b0; b4 = 1'b1; c4 = 1'b0; d4 = 1'b1; s4 = 2'b00;
        #10;
        $display("%0dns\t %b %b %b %b | %b | %b    %b", $time, a4, b4, c4, d4, s4, y4_structural, y4_behavioral);

        // Case 2: s4 = 01, a = 0, b = 1, c = 0, d = 1 => y = 1
        a4 = 1'b0; b4 = 1'b1; c4 = 1'b0; d4 = 1'b1; s4 = 2'b01;
        #10; 
        $display("%0dns\t %b %b %b %b | %b | %b    %b", $time, a4, b4, c4, d4, s4, y4_structural, y4_behavioral);

        // Case 3: s4 = 10, a = 0, b = 1, c = 0, d = 1 => y = 0
        a4 = 1'b0; b4 = 1'b1; c4 = 1'b0; d4 = 1'b1; s4 = 2'b10;
        #10; 
        $display("%0dns\t %b %b %b %b | %b | %b    %b", $time, a4, b4, c4, d4, s4, y4_structural, y4_behavioral);

        // Case 4: s4 = 11, a = 0, b = 1, c = 0, d = 1 => y = 1
        a4 = 1'b0; b4 = 1'b1; c4 = 1'b0; d4 = 1'b1; s4 = 2'b11;
        #10; 
        $display("%0dns\t %b %b %b %b | %b | %b    %b", $time, a4, b4, c4, d4, s4, y4_structural, y4_behavioral);

        // Testbench for MUX 8:1 Structural
        $display("====================================");
        $display("   TESTBENCH MUX 8:1                ");
        $display("====================================");
        $display("Time\t  D (Inputs)   S | Y_Struct");
        $display("------------------------------------");

        d8 = 8'b10100110;

        // Test all 8 cases for s8
        for (i = 0; i < 8; i = i + 1) begin
            s8 = i;
            #10;
            $display("%0dns\t %b | %b | %b", $time, d8, s8, y8_structural);
        end

        // Testbench for Parameterized MUX 2:1
        $display("====================================");
        $display("   TESTBENCH PARAM_MUX 2:1            ");
        $display("====================================");
        $display("Time\t   A  B  S | Y_Param");
        $display("------------------------------------");

        // Case 1: s = 0, a = 0, b = 1 => y = 0
        param_a = 4'b0000; param_b = 4'b1111; param_s = 1'b0;
        #10;
        $display("%0dns\t %b %b %b | %b", $time, param_a, param_b, param_s, param_y);

        // Case 2: s = 1, a = 0, b = 1 => y = 1
        param_a = 4'b0000; param_b = 4'b1111; param_s = 1'b1;
        #10; 
        $display("%0dns\t %b %b %b | %b", $time, param_a, param_b, param_s, param_y);

        // Case 3: s = 0, a = 1, b = 0 => y = 1
        param_a = 4'b1111; param_b = 4'b0000; param_s = 1'b0;
        #10; 
        $display("%0dns\t %b %b %b | %b", $time, param_a, param_b, param_s, param_y);

        // Case 4: s = 1, a = 1, b = 0 => y = 0
        param_a = 4'b1111; param_b = 4'b0000; param_s = 1'b1;
        #10; 
        $display("%0dns\t %b %b %b | %b", $time, param_a, param_b, param_s, param_y);

        $finish();
    end

    initial begin
        $dumpfile("tb_mux.vcd");
        $dumpvars(0, tb_mux);
    end
    
endmodule

Extra_Lab/MUX/tb_mux.vcd
$date
	Thu May 28 10:36:57 2026
$end
$version
	ModelSim Version 2020.1
$end
$timescale
	1ps
$end

$scope module tb_mux $end
$var parameter 32 ! TEST_WIDTH $end
$var reg 1 " a2 $end
$var reg 1 # b2 $end
$var reg 1 $ s2 $end
$var wire 1 % y2_gate $end
$var wire 1 & y2_dataflow $end
$var reg 1 ' a4 $end
$var reg 1 ( b4 $end
$var reg 1 ) c4 $end
$var reg 1 * d4 $end
$var reg 2 + s4 [1:0] $end
$var wire 1 , y4_structural $end
$var wire 1 - y4_behavioral $end
$var reg 8 . d8 [7:0] $end
$var reg 3 / s8 [2:0] $end
$var wire 1 0 y8_structural $end
$var integer 32 1 i $end
$var reg 4 2 param_a [3:0] $end
$var reg 4 3 param_b [3:0] $end
$var reg 1 4 param_s $end
$var wire 1 5 param_y [3] $end
$var wire 1 6 param_y [2] $end
$var wire 1 7 param_y [1] $end
$var wire 1 8 param_y [0] $end

$scope module uut_mux2_gate $end
$var wire 1 9 a $end
$var wire 1 : b $end
$var wire 1 ; s $end
$var wire 1 % y $end
$var wire 1 < not_s $end
$var wire 1 = a_sel $end
$var wire 1 > b_sel $end
$upscope $end

$scope module uut_mux2_dataflow $end
$var wire 1 ? a $end
$var wire 1 @ b $end
$var wire 1 A s $end
$var wire 1 & y $end
$upscope $end

$scope module uut_mux4_structural $end
$var wire 1 B a $end
$var wire 1 C b $end
$var wire 1 D c $end
$var wire 1 E d $end
$var wire 1 F s [1] $end
$var wire 1 G s [0] $end
$var wire 1 , y $end
$var wire 1 H mux_ab $end
$var wire 1 I mux_cd $end

$scope module m1 $end
$var wire 1 B a $end
$var wire 1 C b $end
$var wire 1 G s $end
$var wire 1 H y $end
$upscope $end

$scope module m2 $end
$var wire 1 D a $end
$var wire 1 E b $end
$var wire 1 G s $end
$var wire 1 I y $end
$upscope $end

$scope module m3 $end
$var wire 1 H a $end
$var wire 1 I b $end
$var wire 1 F s $end
$var wire 1 , y $end
$upscope $end
$upscope $end

$scope module uut_mux4_behavioral $end
$var wire 1 J a $end
$var wire 1 K b $end
$var wire 1 L c $end
$var wire 1 M d $end
$var wire 1 N s [1] $end
$var wire 1 O s [0] $end
$var reg 1 P y $end
$upscope $end

$scope module uut_mux8_structural $end
$var wire 1 Q d [7] $end
$var wire 1 R d [6] $end
$var wire 1 S d [5] $end
$var wire 1 T d [4] $end
$var wire 1 U d [3] $end
$var wire 1 V d [2] $end
$var wire 1 W d [1] $end
$var wire 1 X d [0] $end
$var wire 1 Y s [2] $end
$var wire 1 Z s [1] $end
$var wire 1 [ s [0] $end
$var wire 1 0 y $end
$var wire 1 \ mux_lower $end
$var wire 1 ] mux_upper $end

$scope module mux_low $end
$var wire 1 X a $end
$var wire 1 W b $end
$var wire 1 V c $end
$var wire 1 U d $end
$var wire 1 Z s [1] $end
$var wire 1 [ s [0] $end
$var reg 1 ^ y $end
$upscope $end

$scope module mux_high $end
$var wire 1 T a $end
$var wire 1 S b $end
$var wire 1 R c $end
$var wire 1 Q d $end
$var wire 1 Z s [1] $end
$var wire 1 [ s [0] $end
$var reg 1 _ y $end
$upscope $end

$scope module mux_final $end
$var wire 1 \ a $end
$var wire 1 ] b $end
$var wire 1 Y s $end
$var wire 1 0 y $end
$upscope $end
$upscope $end

$scope module uut_param_mux2 $end
$var parameter 32 ` WIDTH $end
$var wire 1 a a [3] $end
$var wire 1 b a [2] $end
$var wire 1 c a [1] $end
$var wire 1 d a [0] $end
$var wire 1 e b [3] $end
$var wire 1 f b [2] $end
$var wire 1 g b [1] $end
$var wire 1 h b [0] $end
$var wire 1 i s $end
$var wire 1 5 y [3] $end
$var wire 1 6 y [2] $end
$var wire 1 7 y [1] $end
$var wire 1 8 y [0] $end
$upscope $end
$upscope $end
$enddefinitions $end
#0
$dumpvars
0"
1#
0$
x'
x(
x)
x*
bx +
bx .
bx /
bx 2
bx 3
x4
xP
x^
x_
b100 !
b100 `
bx 1
0%
0&
x,
x-
x0
1<
0=
0>
x8
x7
x6
x5
xH
xI
x\
x]
xi
xh
xg
xf
xe
xd
xc
xb
xa
x[
xZ
xY
xX
xW
xV
xU
xT
xS
xR
xQ
xO
xN
xM
xL
xK
xJ
xG
xF
xE
xD
xC
xB
0A
1@
0?
0;
1:
09
$end
#10000
1$
1;
1A
1&
1>
0<
1%
#20000
1"
0#
0$
19
1?
0:
0@
0;
0A
0>
1<
0%
1=
1%
#30000
1$
1;
1A
0&
0<
0=
0%
#40000
0'
1(
0)
1*
b0 +
0B
1C
0D
1E
0G
0F
0H
0I
0,
0J
1K
0L
1M
0O
0N
0P
0-
#50000
b1 +
1G
1H
1I
1,
1O
1P
1-
#60000
b10 +
0G
1F
0H
0I
0,
0O
1N
0P
0-
#70000
b11 +
1G
1H
1I
1,
1O
1P
1-
#80000
b10100110 .
b0 1
b0 /
0[
0Z
0Y
0X
1W
1V
0U
0T
1S
0R
1Q
0^
0_
0\
0]
00
#90000
b1 1
b1 /
1[
1^
1_
1\
1]
10
#100000
b10 1
b10 /
0[
1Z
0_
0]
#110000
b11 1
b11 /
1[
0^
1_
0\
1]
00
#120000
b100 1
b100 /
0[
0Z
1Y
10
0_
0]
00
