Lab05_Selectively_Blinking_an_LED/demux_1to4.v
module demux_1to4 (
    input i_data,
    input [1:0] i_sel,
    output o_data_1,
    output o_data_2,
    output o_data_3,
    output o_data_4
);

    assign o_data_1 = (i_sel == 2'b00) ? i_data : 1'b0;
    assign o_data_2 = (i_sel == 2'b01) ? i_data : 1'b0;
    assign o_data_3 = (i_sel == 2'b10) ? i_data : 1'b0;
    assign o_data_4 = (i_sel == 2'b11) ? i_data : 1'b0;

endmodule

Lab05_Selectively_Blinking_an_LED/lfsr_nbit.v
module lfsr_nbit #(
    parameter WIDTH = 23
)(
    input i_clk,
    input i_rst_n,
    output o_lfsr_done
);

    reg [WIDTH-1:0] r_lfsr;
    wire w_feedback;

    // 
    assign w_feedback = (WIDTH == 4) ? ~(r_lfsr[3] ^ r_lfsr[2]) : (WIDTH == 22) ? ~(r_lfsr[21] ^ r_lfsr[20]) : ~(r_lfsr[22] ^ r_lfsr[17]);

    // 
    always @(posedge i_clk or negedge i_rst_n) begin
        if (!i_rst_n) begin
            r_lfsr <= {WIDTH{1'b0}};
        end else begin
            r_lfsr <= {r_lfsr[WIDTH-2:0], w_feedback};
        end
    end

    assign o_lfsr_done = (r_lfsr == 0);

endmodule

Lab05_Selectively_Blinking_an_LED/fap201_lab05.v
module fap201_lab05 #(
    parameter WIDTH = 23
)(
    input i_clk,
    input i_rst_n,
    input i_SW1,
    input i_SW2,
    output o_LED_1,
    output o_LED_2,
    output o_LED_3,
    output o_LED_4
);

    wire w_lfsr_done;
    reg r_toggle;

    lfsr_nbit #(
        .WIDTH(WIDTH)
    ) lfsr_inst (
        .i_clk(i_clk),
        .i_rst_n(i_rst_n),
        .o_lfsr_done(w_lfsr_done)
    );

    always @(posedge i_clk or negedge i_rst_n) begin
        if (!i_rst_n) begin
            r_toggle <= 1'b0;
        end else if (w_lfsr_done) begin
            r_toggle <= ~r_toggle;
        end
    end

    demux_1to4 demux_inst (
        .i_data(r_toggle),
        .i_sel({i_SW2, i_SW1}),
        .o_data_1(o_LED_1),
        .o_data_2(o_LED_2),
        .o_data_3(o_LED_3),
        .o_data_4(o_LED_4)
    );

endmodule

Lab05_Selectively_Blinking_an_LED/tb_fap201_lab05.v
`timescale 1ns/1ps

module tb_fap201_lab05;

    reg clk;
    reg rst_n;
    reg SW1;
    reg SW2;

    wire led1;
    wire led2;
    wire led3;
    wire led4;

    fap201_lab05 #(
        .WIDTH(4)
    ) uut (
        .i_clk(clk),
        .i_rst_n(rst_n),
        .i_SW1(SW1),
        .i_SW2(SW2),
        .o_LED_1(led1),
        .o_LED_2(led2),
        .o_LED_3(led3),
        .o_LED_4(led4)
    );

    always #10 clk = ~clk;

    initial begin
        clk = 0;
        rst_n = 0;
        SW1 = 0;
        SW2 = 0;

        $display("=================================");
        $display("        TESTBENCH LAB05");
        $display("=================================");

        #40;
        rst_n = 1;
        $display("[TIME: %0dns] Start test.", $time);

        // Case 1: SW1 = 0, SW2 = 0 => LED_1
        SW2 = 0; SW1 = 0;
        $display("[TIME: %0dns] SW1 = %b, SW2 = %b => LED_1.", $time, SW1, SW2);
        #1000;

        // Case 2: SW1 = 1, SW2 = 0 => LED_2
        SW2 = 0; SW1 = 1;
        $display("[TIME: %0dns] SW1 = %b, SW2 = %b => LED_2.", $time, SW1, SW2);
        #1000;

        // Case 3: SW1 = 0, SW2 = 1 => LED_3
        SW2 = 1; SW1 = 0;
        $display("[TIME: %0dns] SW1 = %b, SW2 = %b => LED_3.", $time, SW1, SW2);
        #1000;

        // Case 4: SW1 = 1, SW2 = 1 => LED_4
        SW2 = 1; SW1 = 1;
        $display("[TIME: %0dns] SW1 = %b, SW2 = %b => LED_4.", $time, SW1, SW2);
        #1000;

        $display("[TIME: %0dns] Test finished.", $time);
        $finish;
    end

    initial begin
        $dumpfile("tb_fap201_lab05.vcd");
        $dumpvars(0, tb_fap201_lab05);
    end

endmodule

Lab05_Selectively_Blinking_an_LED/tb_fap201_lab05.vcd
$date
	Thu May 28 11:28:15 2026
$end
$version
	ModelSim Version 2020.1
$end
$timescale
	1ps
$end

$scope module tb_fap201_lab05 $end
$var reg 1 ! clk $end
$var reg 1 " rst_n $end
$var reg 1 # SW1 $end
$var reg 1 $ SW2 $end
$var wire 1 % led1 $end
$var wire 1 & led2 $end
$var wire 1 ' led3 $end
$var wire 1 ( led4 $end

$scope module uut $end
$var parameter 32 ) WIDTH $end
$var wire 1 * i_clk $end
$var wire 1 + i_rst_n $end
$var wire 1 , i_SW1 $end
$var wire 1 - i_SW2 $end
$var wire 1 % o_LED_1 $end
$var wire 1 & o_LED_2 $end
$var wire 1 ' o_LED_3 $end
$var wire 1 ( o_LED_4 $end
$var wire 1 . w_lfsr_done $end
$var reg 1 / r_toggle $end

$scope module lfsr_inst $end
$var parameter 32 0 WIDTH $end
$var wire 1 * i_clk $end
$var wire 1 + i_rst_n $end
$var wire 1 . o_lfsr_done $end
$var reg 4 1 r_lfsr [3:0] $end
$var wire 1 2 w_feedback $end
$upscope $end

$scope module demux_inst $end
$var wire 1 3 i_data $end
$var wire 1 - i_sel [1] $end
$var wire 1 , i_sel [0] $end
$var wire 1 % o_data_1 $end
$var wire 1 & o_data_2 $end
$var wire 1 ' o_data_3 $end
$var wire 1 ( o_data_4 $end
$upscope $end
$upscope $end
$upscope $end
$enddefinitions $end
#0
$dumpvars
0!
0"
0#
0$
0/
b0 1
b100 )
b100 0
0%
0&
0'
0(
1.
12
0-
0,
0+
0*
03
$end
#10000
1!
1*
#20000
0!
0*
#30000
1!
1*
#40000
1"
0!
1+
0*
#50000
1!
1*
b1 1
1/
0.
13
1%
#60000
0!
0*
#70000
1!
1*
b11 1
#80000
0!
0*
#90000
1!
1*
b111 1
02
#100000
0!
0*
#110000
1!
1*
b1110 1
12
#120000
0!
0*
#130000
1!
1*
b1101 1
#140000
0!
0*
#150000
1!
1*
b1011 1
02
#160000
0!
0*
#170000
1!
1*
b110 1
#180000
0!
0*
#190000
1!
1*
b1100 1
12
#200000
0!
0*
#210000
1!
1*
b1001 1
02
#220000
0!
0*
#230000
1!
1*
b10 1
12
#240000
0!
0*
#250000
1!
1*
b101 1
02
#260000
0!
0*
#270000
1!
1*
b1010 1
#280000
0!
0*
#290000
1!
1*
b100 1
#300000
0!
0*
#310000
1!
1*
b1000 1
#320000
0!
0*
#330000
1!
1*
b0 1
1.
12
#340000
0!
0*
#350000
1!
1*
b1 1
0/
0.
03
0%
#360000
0!
0*
#370000
1!
1*
b11 1
#380000
0!
0*
#390000
1!
1*
b111 1
02
#400000
0!
0*
#410000
1!
1*
b1110 1
12
#420000
0!
0*
#430000
1!
1*
b1101 1
#440000
0!
0*
#450000
1!
1*
b1011 1
02
#460000
0!
0*
#470000
1!
1*
b110 1
#480000
0!
0*
#490000
1!
1*
b1100 1
12
#500000
0!
0*
#510000
1!
1*
b1001 1
02
#520000
0!
0*
#530000
1!
1*
b10 1
12
#540000
0!
0*
#550000
1!
1*
b101 1
02
#560000
0!
0*
#570000
1!
1*
b1010 1
#580000
0!
0*
#590000
1!
1*
b100 1
#600000
0!
0*
#610000
1!
1*
b1000 1
#620000
0!
0*
#630000
1!
1*
b0 1
1.
12
#640000
0!
0*
#650000
1!
1*
b1 1
1/
0.
13
1%
#660000
0!
0*
#670000
1!
1*
b11 1
#680000
0!
0*
#690000
1!
1*
b111 1
02
#700000
0!
0*
#710000
1!
1*
b1110 1
12
#720000
0!
0*
#730000
1!
1*
b1101 1
#740000
0!
0*
#750000
1!
1*
b1011 1
02
#760000
0!
0*
#770000
1!
1*
b110 1
#780000
0!
0*
#790000
1!
1*
b1100 1
12
#800000
0!
0*
#810000
1!
1*
b1001 1
02
#820000
0!
0*
#830000
1!
1*
b10 1
12
#840000
0!
0*
#850000
1!
1*
b101 1
02
#860000
0!
0*
#870000
1!
1*
b1010 1
#880000
0!
0*
#890000
1!
1*
b100 1
#900000
0!
0*
#910000
1!
1*
b1000 1
#920000
0!
0*
#930000
1!
1*
b0 1
1.
12
#940000
0!
0*
#950000
1!
1*
b1 1
0/
0.
03
0%
#960000
0!
0*
#970000
1!
1*
b11 1
#980000
0!
0*
#990000
1!
1*
b111 1
02
#1000000
0!
0*
#1010000
1!
1*
b1110 1
12
#1020000
0!
0*
#1030000
1!
1*
b1101 1
#1040000
1#
0!
1,
0*
#1050000
1!
1*
b1011 1
02
#1060000
0!
0*
#1070000
1!
1*
b110 1
#1080000
0!
0*
#1090000
1!
1*
b1100 1
12
#1100000
0!
0*
#1110000
1!
1*
b1001 1
02
#1120000
0!
0*
#1130000
1!
1*
b10 1
12
#1140000
0!
0*
#1150000
1!
1*
b101 1
02
#1160000
0!
0*
#1170000
1!
1*
b1010 1
#1180000
0!
0*
#1190000
1!
1*
b100 1
#1200000
0!
0*
#1210000
1!
1*
b1000 1
#1220000
0!
0*
#1230000
1!
1*
b0 1
1.
12
#1240000
0!
0*
#1250000
1!
1*
b1 1
1/
0.
13
1&
#1260000
0!
0*
#1270000
1!
1*
b11 1
#1280000
0!
0*
#1290000
1!
1*
b111 1
02
#1300000
0!
0*
#1310000
1!
1*
b1110 1
12
#1320000
0!
0*
#1330000
1!
1*
b1101 1
#1340000
0!
0*
#1350000
1!
1*
b1011 1
02
#1360000
0!
0*
#1370000
1!
1*
b110 1
#1380000
0!
0*
#1390000
1!
1*
b1100 1
12
#1400000
0!
0*
#1410000
1!
1*
b1001 1
02
#1420000
0!
0*
#1430000
1!
1*
b10 1
12
#1440000
0!
0*
#1450000
1!
1*
b101 1
02
#1460000
0!
0*
#1470000
1!
1*
b1010 1
#1480000
0!
0*
#1490000
1!
1*
b100 1
#1500000
0!
0*
#1510000
1!
1*
b1000 1
#1520000
0!
0*
#1530000
1!
1*
b0 1
1.
12
#1540000
0!
0*
#1550000
1!
1*
b1 1
0/
0.
03
0&
#1560000
0!
0*
#1570000
1!
1*
b11 1
#1580000
0!
0*
#1590000
1!
1*
b111 1
02
#1600000
0!
0*
#1610000
1!
1*
b1110 1
12
#1620000
0!
0*
#1630000
1!
1*
b1101 1
#1640000
0!
0*
#1650000
1!
1*
b1011 1
02
#1660000
0!
0*
#1670000
1!
1*
b110 1
#1680000
0!
0*
#1690000
1!
1*
b1100 1
12
#1700000
0!
0*
#1710000
1!
1*
b1001 1
02
#1720000
0!
0*
#1730000
1!
1*
b10 1
12
#1740000
0!
0*
#1750000
1!
1*
b101 1
02
#1760000
0!
0*
#1770000
1!
1*
b1010 1
#1780000
0!
0*
#1790000
1!
1*
b100 1
#1800000
0!
0*
#1810000
1!
1*
b1000 1
#1820000
0!
0*
#1830000
1!
1*
b0 1
1.
12
#1840000
0!
0*
#1850000
1!
1*
b1 1
1/
0.
13
1&
#1860000
0!
0*
#1870000
1!
1*
b11 1
#1880000
0!
0*
#1890000
1!
1*
b111 1
02
#1900000
0!
0*
#1910000
1!
1*
b1110 1
12
#1920000
0!
0*
#1930000
1!
1*
b1101 1
#1940000
0!
0*
#1950000
1!
1*
b1011 1
02
#1960000
0!
0*
#1970000
1!
1*
b110 1
#1980000
0!
0*
#1990000
1!
1*
b1100 1
12
#2000000
0!
0*
#2010000
1!
1*
b1001 1
02
#2020000
0!
0*
#2030000
1!
1*
b10 1
12
#2040000
1$
0#
0!
1-
0,
1'
0&
0*
#2050000
1!
1*
b101 1
02
#2060000
0!
0*
#2070000
1!
1*
b1010 1
#2080000
0!
0*
#2090000
1!
1*
b100 1
#2100000
0!
0*
#2110000
1!
1*
b1000 1
#2120000
0!
0*
#2130000
1!
1*
b0 1
1.
12
#2140000
0!
0*
#2150000
1!
1*
b1 1
0/
0.
03
0'
#2160000
0!
0*
#2170000
1!
1*
b11 1
#2180000
0!
0*
#2190000
1!
1*
b111 1
02
#2200000
0!
0*
#2210000
1!
1*
b1110 1
12
#2220000
0!
0*
#2230000
1!
1*
b1101 1
#2240000
0!
0*
#2250000
1!
1*
b1011 1
02
#2260000
0!
0*
#2270000
1!
1*
b110 1
#2280000
0!
0*
#2290000
1!
1*
b1100 1
12
#2300000
0!
0*
#2310000
1!
1*
b1001 1
02
#2320000
0!
0*
#2330000
1!
1*
b10 1
12
#2340000
0!
0*
#2350000
1!
1*
b101 1
02
#2360000
0!
0*
#2370000
1!
1*
b1010 1
#2380000
0!
0*
#2390000
1!
1*
b100 1
#2400000
0!
0*
#2410000
1!
1*
b1000 1
#2420000
0!
0*
#2430000
1!
1*
b0 1
1.
12
#2440000
0!
0*
#2450000
1!
1*
b1 1
1/
0.
13
1'
#2460000
0!
0*
#2470000
1!
1*
b11 1
#2480000
0!
0*
#2490000
1!
1*
b111 1
02
#2500000
0!
0*
#2510000
1!
1*
b1110 1
12
#2520000
0!
0*
#2530000
1!
1*
b1101 1
#2540000
0!
0*
#2550000
1!
1*
b1011 1
02
#2560000
0!
0*
#2570000
1!
1*
b110 1
#2580000
0!
0*
#2590000
1!
1*
b1100 1
12
#2600000
0!
0*
#2610000
1!
1*
b1001 1
02
#2620000
0!
0*
#2630000
1!
1*
b10 1
12
#2640000
0!
0*
#2650000
1!
1*
b101 1
02
#2660000
0!
0*
#2670000
1!
1*
b1010 1
#2680000
0!
0*
#2690000
1!
1*
b100 1
#2700000
0!
0*
#2710000
1!
1*
b1000 1
#2720000
0!
0*
#2730000
1!
1*
b0 1
1.
12
#2740000
0!
0*
#2750000
1!
1*
b1 1
0/
0.
03
0'
#2760000
0!
0*
#2770000
1!
1*
b11 1
#2780000
0!
0*
#2790000
1!
1*
b111 1
02
#2800000
0!
0*
#2810000
1!
1*
b1110 1
12
#2820000
0!
0*
#2830000
1!
1*
b1101 1
#2840000
0!
0*
#2850000
1!
1*
b1011 1
02
#2860000
0!
0*
#2870000
1!
1*
b110 1
#2880000
0!
0*
#2890000
1!
1*
b1100 1
12
#2900000
0!
0*
#2910000
1!
1*
b1001 1
02
#2920000
0!
0*
#2930000
1!
1*
b10 1
12
#2940000
0!
0*
#2950000
1!
1*
b101 1
02
#2960000
0!
0*
#2970000
1!
1*
b1010 1
#2980000
0!
0*
#2990000
1!
1*
b100 1
#3000000
0!
0*
#3010000
1!
1*
b1000 1
#3020000
0!
0*
#3030000
1!
1*
b0 1
1.
12
#3040000
1#
0!
1,
0*
#3050000
1!
1*
b1 1
1/
0.
13
1(
#3060000
0!
0*
#3070000
1!
1*
b11 1
#3080000
0!
0*
#3090000
1!
1*
b111 1
02
#3100000
0!
0*
#3110000
1!
1*
b1110 1
12
#3120000
0!
0*
#3130000
1!
1*
b1101 1
#3140000
0!
0*
#3150000
1!
1*
b1011 1
02
#3160000
0!
0*
#3170000
1!
1*
b110 1
#3180000
0!
0*
#3190000
1!
1*
b1100 1
12
#3200000
0!
0*
#3210000
1!
1*
b1001 1
02
#3220000
0!
0*
#3230000
1!
1*
b10 1
12
#3240000
0!
0*
#3250000
1!
1*
b101 1
02
#3260000
0!
0*
#3270000
1!
1*
b1010 1
#3280000
0!
0*
#3290000
1!
1*
b100 1
#3300000
0!
0*
#3310000
1!
1*
b1000 1
#3320000
0!
0*
#3330000
1!
1*
b0 1
1.
12
#3340000
0!
0*
#3350000
1!
1*
b1 1
0/
0.
03
0(
#3360000
0!
0*
#3370000
1!
1*
b11 1
#3380000
0!
0*
#3390000
1!
1*
b111 1
02
#3400000
0!
0*
#3410000
1!
1*
b1110 1
12
#3420000
0!
0*
#3430000
1!
1*
b1101 1
#3440000
0!
0*
#3450000
1!
1*
b1011 1
02
#3460000
0!
0*
#3470000
1!
1*
b110 1
#3480000
0!
0*
#3490000
1!
1*
b1100 1
12
#3500000
0!
0*
#3510000
1!
1*
b1001 1
02
#3520000
0!
0*
#3530000
1!
1*
b10 1
12
#3540000
0!
0*
#3550000
1!
1*
b101 1
